prompy/DocumentationGenerator.py
prompy/ProMExecutor.py
prompy/ProcessDiscovery.py
prompy/ScriptBuilder.py
prompy/__init__.py
prompy/__main__.py
prompy/utils.py
prompy-1.3.0.dist-info/DESCRIPTION.rst
prompy-1.3.0.dist-info/METADATA
prompy-1.3.0.dist-info/RECORD
prompy-1.3.0.dist-info/WHEEL
prompy-1.3.0.dist-info/metadata.json
prompy-1.3.0.dist-info/top_level.txt
