Metadata-Version: 2.0
Name: prompy
Version: 1.3.0
Summary: prompy
Home-page: https://github.com/
Author: Dominique Sommers
Author-email: dominiquesommers88@gmail.com
License: MIT
Platform: UNKNOWN
Classifier: License :: OSI Approved :: MIT License
Classifier: Programming Language :: Python :: 3
Classifier: Programming Language :: Python :: 3.7
